{
  "models": {
    "Vespa Primavera 150 3v": {
      "categories": {
        "Genel": {
          "parts": [
            "83bdb4cd",
            "217213c4",
            "8d06836b",
            "aafff02c",
            "e2148ce6",
            "f7c26242",
            "e2437873",
            "42b2db5b",
            "8ae12743",
            "d2ac1e4d",
            "0ee73b9d",
            "9e12e0d9",
            "a85fb291",
            "5d758510",
            "d4667c19",
            "e329c7a6",
            "5668363b",
            "514ed2c6",
            "3b4b8a77",
            "d09919b3",
            "819870c6",
            "4269cd21",
            "7c77b395",
            "fa116a70",
            "138f58df",
            "786ec500",
            "2e4c9c21",
            "7b61fb15",
            "8322a6dc",
            "fd4b6ff8",
            "e35d45f6",
            "a2a4cf4a",
            "eafee8e5",
            "84d1fd2c",
            "1adbb3f8",
            "ff6670d6",
            "7632f712",
            "dbd68a4b",
            "1654dbf5",
            "31abcccb",
            "1aafc558",
            "64b48d29",
            "5884d944",
            "d05b2713",
            "73c651f3",
            "ff6c9569",
            "5873ced8",
            "989402cf",
            "61e0224c",
            "529a5b3f",
            "70deb902",
            "3283de20",
            "3e4447ff",
            "34806ace",
            "a98b1bcf",
            "93950f3e",
            "c37b8881",
            "54e13fde",
            "bed025b9",
            "0bb40833",
            "9a6a18e8",
            "7ce4c948",
            "a619f1e9",
            "bd6e33b2",
            "2461c07c",
            "804d2277",
            "a6b71644"
          ],
          "url": "https://www.motopit.com.tr/kategori/vespa-primavera-150-3v-yedek-parca"
        }
      },
      "url": "https://www.motopit.com.tr/kategori/vespa-primavera-150-3v-yedek-parca"
    },
    "Vespa GTS 300": {
      "categories": {
        "Genel": {
          "parts": [
            "325aef78",
            "83bdb4cd",
            "217213c4",
            "cab31b60",
            "aafff02c",
            "1ca73a85",
            "8417a0e8",
            "d29e18af",
            "c239bad7",
            "95202d2b",
            "3a2bd750",
            "308735e3",
            "785be309",
            "8ae12743",
            "b93661db",
            "d2ac1e4d",
            "9e12e0d9",
            "e329c7a6",
            "f8b9d1ec",
            "c1b4f5d8",
            "d0c570a0",
            "2d4c60d9",
            "dd8ed1a2",
            "e531699c",
            "365057e1",
            "fb3b1472",
            "819870c6",
            "7c77b395",
            "932a19f1",
            "a94bfe3c",
            "4110b69c",
            "86be2488",
            "138f58df",
            "911e949d",
            "c731f7cb",
            "a3758221",
            "6037a07d",
            "651ccff6",
            "690bf101",
            "2ec71271",
            "7399054a",
            "e35d45f6",
            "adec4789",
            "d78a8e10",
            "a036fa48",
            "1a5bc5bd",
            "4292c05b",
            "f9e5a80e",
            "339b594c",
            "dc125b44",
            "8958e34d",
            "9f2d4b5b",
            "df2727b8",
            "17b62a90",
            "a3e57e3d",
            "b2e21a6e",
            "5884d944",
            "d05b2713",
            "73c651f3",
            "4c92e615",
            "5873ced8",
            "989402cf",
            "61e0224c",
            "529a5b3f",
            "016c1726",
            "81180c74",
            "3e4447ff"
          ],
          "url": "https://www.motopit.com.tr/kategori/vespa-gts-300-yedek-parca"
        }
      },
      "url": "https://www.motopit.com.tr/kategori/vespa-gts-300-yedek-parca"
    },
    "Vespa Sprint 125": {
      "categories": {
        "Genel": {
          "parts": [
            "83bdb4cd",
            "217213c4",
            "8d06836b",
            "aafff02c",
            "e2148ce6",
            "f7c26242",
            "e2437873",
            "231e199b",
            "9e12e0d9",
            "e329c7a6",
            "5668363b",
            "3b4b8a77",
            "89175a23",
            "819870c6",
            "4269cd21",
            "7c77b395",
            "fa116a70",
            "138f58df",
            "2cf92601",
            "2b15e494",
            "2e4c9c21",
            "7b61fb15",
            "7c8ad0dd",
            "e35d45f6",
            "a2a4cf4a",
            "eafee8e5",
            "84d1fd2c",
            "1adbb3f8",
            "ff6670d6",
            "7632f712",
            "64b48d29",
            "5884d944",
            "d05b2713",
            "73c651f3",
            "ff6c9569",
            "5873ced8",
            "989402cf",
            "61e0224c",
            "529a5b3f",
            "70deb902",
            "3283de20",
            "34806ace",
            "a98b1bcf",
            "93950f3e",
            "c37b8881",
            "54e13fde",
            "bed025b9",
            "0bb40833",
            "9a6a18e8",
            "7ce4c948",
            "2461c07c",
            "804d2277",
            "a6b71644",
            "e5db7512",
            "ceae306c",
            "9edcbb34",
            "2ad12163",
            "dd45d88d",
            "5d446e85",
            "d32eb76f",
            "583b8974",
            "084a965b",
            "db2bbfa3",
            "d99be6d7",
            "ea2eaa47",
            "05fe64eb",
            "6b206fca"
          ],
          "url": "https://www.motopit.com.tr/kategori/vespa-sprint-125-3v-ie-yedek-parca"
        }
      },
      "url": "https://www.motopit.com.tr/kategori/vespa-sprint-125-3v-ie-yedek-parca"
    },
    "Vespa ET4 150": {
      "categories": {
        "Genel": {
          "parts": [
            "37836878",
            "83bdb4cd",
            "217213c4",
            "348e9fa2",
            "aafff02c",
            "a61ad0f2",
            "f7c26242",
            "e2437873",
            "c239bad7",
            "ae275147",
            "59bfdce2",
            "35e29573",
            "34b9c39e",
            "67da7a7c",
            "ca54e664",
            "e329c7a6",
            "80d29ae0",
            "fb3b1472",
            "819870c6",
            "fa116a70",
            "e6db655e",
            "138f58df",
            "911e949d",
            "241fa1b8",
            "a3758221",
            "2cf92601",
            "2b15e494",
            "5622ae72",
            "7ce672fc",
            "f9a26f9e",
            "3eace369",
            "198eb6b7",
            "571eb4c5",
            "4110fad6",
            "9f2d4b5b",
            "df2727b8",
            "e7c66f2c",
            "85a1b3c8",
            "a07314ee",
            "5884d944",
            "73c651f3",
            "0e4527cd",
            "4c92e615",
            "5873ced8",
            "989402cf",
            "ded0f5a9",
            "529a5b3f",
            "016c1726",
            "7ff5beb2",
            "81180c74",
            "3e4447ff",
            "fc542057",
            "93950f3e",
            "ae9233b8",
            "0d471497",
            "b52e29c2",
            "457db060",
            "ec4a9908",
            "d32eb76f",
            "583b8974",
            "084a965b",
            "05fe64eb",
            "c0491d8c",
            "623063a0",
            "35a82a01",
            "a01e3f4b",
            "2fc41427",
            "6a45732f"
          ],
          "url": "https://www.motopit.com.tr/kategori/vespa-et4-150-yedek-parca"
        }
      },
      "url": "https://www.motopit.com.tr/kategori/vespa-et4-150-yedek-parca"
    },
    "Vespa LX 150": {
      "categories": {
        "Genel": {
          "parts": [
            "37836878",
            "83bdb4cd",
            "217213c4",
            "2f04b6e1",
            "8f2731fb",
            "aafff02c",
            "a61ad0f2",
            "f7c26242",
            "e2437873",
            "c239bad7",
            "ae275147",
            "ec04013e",
            "8ae12743",
            "d2ac1e4d",
            "9e121914",
            "ee7407a7",
            "e329c7a6",
            "80d29ae0",
            "0b167950",
            "fb3b1472",
            "819870c6",
            "a94bfe3c",
            "fa116a70",
            "e6db655e",
            "138f58df",
            "911e949d",
            "a3758221",
            "2cf92601",
            "2b15e494",
            "95c5aeef",
            "198eb6b7",
            "571eb4c5",
            "e35d45f6",
            "eafee8e5",
            "fc030379",
            "e0daa881",
            "b3cd1dfa",
            "1aafc558",
            "f9e623f1",
            "9f2d4b5b",
            "df2727b8",
            "85a1b3c8",
            "5884d944",
            "d05b2713",
            "73c651f3",
            "4c92e615",
            "5873ced8",
            "989402cf",
            "ded0f5a9",
            "529a5b3f",
            "016c1726",
            "81180c74",
            "3e4447ff",
            "93950f3e",
            "0d471497",
            "f7800380",
            "f8d68abd",
            "457db060",
            "ec4a9908",
            "d32eb76f",
            "583b8974",
            "084a965b",
            "e97baf99",
            "810c829d",
            "05fe64eb",
            "35a82a01",
            "23020eba",
            "2fc41427",
            "6a45732f"
          ],
          "url": "https://www.motopit.com.tr/kategori/vespa-lx-150-ie-yedek-parca"
        }
      },
      "url": "https://www.motopit.com.tr/kategori/vespa-lx-150-ie-yedek-parca"
    },
    "Vespa GTS 250": {
      "categories": {
        "Genel": {
          "parts": [
            "83bdb4cd",
            "217213c4",
            "cab31b60",
            "996dbebe",
            "aafff02c",
            "1ca73a85",
            "8417a0e8",
            "d29e18af",
            "c239bad7",
            "95202d2b",
            "3a2bd750",
            "308735e3",
            "785be309",
            "8ae12743",
            "b93661db",
            "94976022",
            "d2ac1e4d",
            "ee7407a7",
            "e329c7a6",
            "f8b9d1ec",
            "d0c570a0",
            "2d4c60d9",
            "dd8ed1a2",
            "e531699c",
            "365057e1",
            "fb3b1472",
            "819870c6",
            "7c77b395",
            "932a19f1",
            "a94bfe3c",
            "4110b69c",
            "036f1605",
            "86be2488",
            "138f58df",
            "911e949d",
            "c731f7cb",
            "a3758221",
            "6037a07d",
            "651ccff6",
            "00219f9d",
            "859403e6",
            "690bf101",
            "2ec71271",
            "7399054a",
            "e35d45f6",
            "0033edbe",
            "adec4789",
            "d78a8e10",
            "4292c05b",
            "f9e5a80e",
            "339b594c",
            "e33022c9",
            "9f2d4b5b",
            "df2727b8",
            "17b62a90",
            "a3e57e3d",
            "b2e21a6e",
            "5884d944",
            "d05b2713",
            "73c651f3",
            "4c92e615",
            "5873ced8",
            "989402cf",
            "61e0224c",
            "529a5b3f",
            "016c1726",
            "fd391445"
          ],
          "url": "https://www.motopit.com.tr/kategori/vespa-gts-250-yedek-parca"
        }
      },
      "url": "https://www.motopit.com.tr/kategori/vespa-gts-250-yedek-parca"
    },
    "Vespa Primavera 125": {
      "categories": {
        "Genel": {
          "parts": [],
          "url": "https://www.motopit.com.tr/kategori/vespa-primavera-125-yedek-parca"
        }
      },
      "url": "https://www.motopit.com.tr/kategori/vespa-primavera-125-yedek-parca"
    }
  },
  "total_models": 7,
  "generated_at": "2025-07-11 10:22:35"
}